django_goodgrids/__init__.py
django_goodgrids/goodgrids.py
django_goodgrids/views.py
django_goodgrids-0.1.3.dist-info/LICENSE.txt
django_goodgrids-0.1.3.dist-info/METADATA
django_goodgrids-0.1.3.dist-info/RECORD
django_goodgrids-0.1.3.dist-info/WHEEL
django_goodgrids-0.1.3.dist-info/top_level.txt
