Metadata-Version: 2.1
Name: django-goodgrids
Version: 0.1.3
Summary: Create Excel files from CSVs using the GoodGrids API, based on an example Excel file template.
Home-page: https://github.com/goodgrids/django-goodgrids
Author: Evertabs LLC
Author-email: support@goodgrids.com
License: MIT License
Project-URL: GoodGrids, https://goodgrids.com
Project-URL: Source, https://github.com/goodgrids/django-goodgrids
Project-URL: PyPi, https://pypi.org/project/django-goodgrids
Project-URL: Tracker, https://github.com/goodgrids/django-goodgrids/issues
Keywords: csv excel spreadsheet conversion
Platform: UNKNOWN
Classifier: Development Status :: 4 - Beta
Classifier: Environment :: Web Environment
Classifier: Framework :: Django
Classifier: Framework :: Django :: 1.11
Classifier: Framework :: Django :: 2.0
Classifier: Intended Audience :: Developers
Classifier: License :: OSI Approved :: MIT License
Classifier: Operating System :: OS Independent
Classifier: Programming Language :: Python
Classifier: Programming Language :: Python :: 2
Classifier: Programming Language :: Python :: 2.7
Classifier: Programming Language :: Python :: 3
Classifier: Programming Language :: Python :: 3.4
Classifier: Programming Language :: Python :: 3.5
Classifier: Programming Language :: Python :: 3.6
Classifier: Programming Language :: Python :: Implementation :: CPython
Classifier: Programming Language :: Python :: Implementation :: PyPy
Classifier: Topic :: Office/Business
Classifier: Topic :: Utilities
Classifier: Topic :: Office/Business :: Office Suites
Classifier: Topic :: Office/Business :: Financial :: Spreadsheet
Requires-Python: >=2.7, !=3.0.*, !=3.1.*, !=3.2.*, !=3.3.*
Requires-Dist: Django (>=1.11)
Requires-Dist: requests (>=2)
